<?xml version="1.0"?>
<Runs>
<Results>
   <Depth>0</Depth>
   <BVC>V34_i</BVC>
   <BVC>V39_env</BVC>
   <BVC>V36_a</BVC>
   <BVC>V123_First</BVC>
   <BVC>OK</BVC>
</Results>
<Results>
   <Depth>1</Depth>
   <BVC>V115_First</BVC>
   <BVC>V34_i</BVC>
   <BVC>V39_env</BVC>
   <BVC>V36_a</BVC>
   <BVC>V123_First</BVC>
   <BVC>OK</BVC>
</Results>
<Results>
   <Depth>2</Depth>
   <BVC>V115_First</BVC>
   <BVC>V34_i</BVC>
   <BVC>V88_garde1</BVC>
   <BVC>V39_env</BVC>
   <BVC>V107_Sofar</BVC>
   <BVC>V123_First</BVC>
   <BVC>OK</BVC>
   <BVC>V37_o1</BVC>
</Results>
<Results>
   <Depth>3</Depth>
   <BVC>V115_First</BVC>
   <BVC>V34_i</BVC>
   <BVC>V88_garde1</BVC>
   <BVC>V39_env</BVC>
   <BVC>V107_Sofar</BVC>
   <BVC>V123_First</BVC>
   <BVC>OK</BVC>
   <BVC>V37_o1</BVC>
</Results>
<Results>
   <Depth>4</Depth>
   <BVC>V115_First</BVC>
   <BVC>V34_i</BVC>
   <BVC>V88_garde1</BVC>
   <BVC>V39_env</BVC>
   <BVC>V107_Sofar</BVC>
   <BVC>V123_First</BVC>
   <BVC>OK</BVC>
   <BVC>V37_o1</BVC>
</Results>
<Results>
   <Depth>5</Depth>
   <BVC>V115_First</BVC>
   <BVC>V34_i</BVC>
   <BVC>V88_garde1</BVC>
   <BVC>V39_env</BVC>
   <BVC>V107_Sofar</BVC>
   <BVC>V123_First</BVC>
   <BVC>OK</BVC>
   <BVC>V37_o1</BVC>
</Results>
<Results>
   <Depth>6</Depth>
   <BVC>V115_First</BVC>
   <BVC>V34_i</BVC>
   <BVC>V88_garde1</BVC>
   <BVC>V39_env</BVC>
   <BVC>V107_Sofar</BVC>
   <BVC>V123_First</BVC>
   <BVC>OK</BVC>
   <BVC>V37_o1</BVC>
</Results>
<Results>
   <Depth>7</Depth>
   <BVC>V115_First</BVC>
   <BVC>V34_i</BVC>
   <BVC>V88_garde1</BVC>
   <BVC>V39_env</BVC>
   <BVC>V107_Sofar</BVC>
   <BVC>V123_First</BVC>
   <BVC>OK</BVC>
   <BVC>V37_o1</BVC>
</Results>
<Results>
   <Depth>8</Depth>
   <BVC>V115_First</BVC>
   <BVC>V34_i</BVC>
   <BVC>V88_garde1</BVC>
   <BVC>V39_env</BVC>
   <BVC>V107_Sofar</BVC>
   <BVC>V123_First</BVC>
   <BVC>OK</BVC>
   <BVC>V37_o1</BVC>
</Results>
<Results>
   <Depth>9</Depth>
   <BVC>V115_First</BVC>
   <BVC>V34_i</BVC>
   <BVC>V88_garde1</BVC>
   <BVC>V39_env</BVC>
   <BVC>V107_Sofar</BVC>
   <BVC>V123_First</BVC>
   <BVC>OK</BVC>
   <BVC>V37_o1</BVC>
</Results>
</Runs>