<?xml version="1.0"?>
<Results xmlns:xsi="http://www.w3.org/2001/XMLSchema-instance">
  <Progress source="bmc" trueFor="1">
    <PropertyProgress name="OK"/>
  </Progress>
  <Progress source="bmc" trueFor="2">
    <PropertyProgress name="OK"/>
  </Progress>
  <Progress source="bmc" trueFor="3">
    <PropertyProgress name="OK"/>
  </Progress>
  <Progress source="bmc" trueFor="4">
    <PropertyProgress name="OK"/>
  </Progress>
  <Progress source="bmc" trueFor="5">
    <PropertyProgress name="OK"/>
  </Progress>
  <Progress source="bmc" trueFor="6">
    <PropertyProgress name="OK"/>
  </Progress>
  <Progress source="bmc" trueFor="7">
    <PropertyProgress name="OK"/>
  </Progress>
  <Progress source="bmc" trueFor="8">
    <PropertyProgress name="OK"/>
  </Progress>
  <Progress source="bmc" trueFor="9">
    <PropertyProgress name="OK"/>
  </Progress>
  <Progress source="bmc" trueFor="10">
    <PropertyProgress name="OK"/>
  </Progress>
  <Progress source="bmc" trueFor="11">
    <PropertyProgress name="OK"/>
  </Progress>
  <Progress source="bmc" trueFor="12">
    <PropertyProgress name="OK"/>
  </Progress>
  <Progress source="bmc" trueFor="13">
    <PropertyProgress name="OK"/>
  </Progress>
  <Progress source="bmc" trueFor="14">
    <PropertyProgress name="OK"/>
  </Progress>
  <Progress source="bmc" trueFor="15">
    <PropertyProgress name="OK"/>
  </Progress>
  <Property name="OK">
    <Runtime unit="sec">17.932</Runtime>
    <Answer source="invariant-generation">valid</Answer>
    <K>1</K>
    <NumberOfIVCs>4</NumberOfIVCs>
    <MustElem>shared</MustElem>
    <MustElem>excludes8~0.X7</MustElem>
    <MustElem>procs</MustElem>
    <MustElem>excludes8~0.X8</MustElem>
    <MustElem>excludes8~0.X6</MustElem>
    <MustElem>excludes8~0.X3</MustElem>
    <MustElem>excludes8~0.X4</MustElem>
    <MustElem>excludes8~0.X1</MustElem>
    <MustElem>Sofar~0.Sofar</MustElem>
    <MustElem>excludes8~0.X2</MustElem>
    <MustElem>firefly~0.invalid</MustElem>
    <MustElem>excludes8~0.excludes</MustElem>
    <MustElem>exclusive</MustElem>
    <MustElem>OK</MustElem>
    <MustElem>First~0.X</MustElem>
    <MustElem>dirty</MustElem>
    <MustElem>Sofar~0.X</MustElem>
    <MustElem>firefly~0.dirty</MustElem>
    <MustElem>firefly~0.e1</MustElem>
    <MustElem>firefly~0.i_invalid</MustElem>
    <MustElem>firefly~0.e4</MustElem>
    <MustElem>env</MustElem>
    <MustElem>firefly~0.e2</MustElem>
    <MustElem>firefly~0.e3</MustElem>
    <MustElem>firefly~0.e8</MustElem>
    <MustElem>firefly~0.e6</MustElem>
    <MustElem>firefly~0.shared</MustElem>
    <MustElem>firefly~0.e7</MustElem>
    <MustElem>First~0.First</MustElem>
    <MustElem>invalid</MustElem>
    <MustElem>firefly~0.garde5</MustElem>
    <MustElem>firefly~0.garde4</MustElem>
    <MustElem>firefly~0.mem_invalid</MustElem>
    <MustElem>firefly~0.exclusive</MustElem>
    <IvcSet number="1">
    <Invariant>((((firefly~0.invalid &lt;= 0) or (0 &lt;= firefly~0.shared)) or (not Sofar~0.Sofar)) or (not (0 &lt;= (firefly~0.exclusive + (-1)))))</Invariant>
    <Invariant>(not (firefly~0.dirty &lt;= (-1)))</Invariant>
    <Invariant>(((not (0 &lt;= (firefly~0.shared + (-1)))) or (not Sofar~0.Sofar)) or (0 &lt;= (firefly~0.shared + (-2))))</Invariant>
    <Invariant>((((firefly~0.invalid &lt;= 0) or (0 &lt;= firefly~0.shared)) or (not Sofar~0.Sofar)) or (not (0 &lt;= (firefly~0.dirty + (-1)))))</Invariant>
    <Invariant>(((0 &lt;= firefly~0.shared) or (not Sofar~0.Sofar)) or (firefly~0.invalid &lt;= (First~0.First + (-3))))</Invariant>
    <Invariant>(First~0.First &lt;= (First~0.First + firefly~0.exclusive))</Invariant>
    <Invariant>OK</Invariant>
    <Invariant>((First~0.First &lt;= 4) or (not Sofar~0.Sofar))</Invariant>
    <Ivc>shared</Ivc>
    <Ivc>excludes8~0.X7</Ivc>
    <Ivc>procs</Ivc>
    <Ivc>excludes8~0.X8</Ivc>
    <Ivc>excludes8~0.X6</Ivc>
    <Ivc>excludes8~0.X3</Ivc>
    <Ivc>excludes8~0.X4</Ivc>
    <Ivc>excludes8~0.X1</Ivc>
    <Ivc>Sofar~0.Sofar</Ivc>
    <Ivc>excludes8~0.X2</Ivc>
    <Ivc>firefly~0.invalid</Ivc>
    <Ivc>excludes8~0.excludes</Ivc>
    <Ivc>exclusive</Ivc>
    <Ivc>OK</Ivc>
    <Ivc>First~0.X</Ivc>
    <Ivc>dirty</Ivc>
    <Ivc>Sofar~0.X</Ivc>
    <Ivc>firefly~0.dirty</Ivc>
    <Ivc>firefly~0.e1</Ivc>
    <Ivc>firefly~0.i_invalid</Ivc>
    <Ivc>firefly~0.e4</Ivc>
    <Ivc>env</Ivc>
    <Ivc>firefly~0.e2</Ivc>
    <Ivc>firefly~0.e3</Ivc>
    <Ivc>firefly~0.e8</Ivc>
    <Ivc>firefly~0.shared</Ivc>
    <Ivc>firefly~0.e6</Ivc>
    <Ivc>firefly~0.e7</Ivc>
    <Ivc>First~0.First</Ivc>
    <Ivc>firefly~0.garde3</Ivc>
    <Ivc>invalid</Ivc>
    <Ivc>firefly~0.garde2</Ivc>
    <Ivc>firefly~0.garde5</Ivc>
    <Ivc>firefly~0.garde4</Ivc>
    <Ivc>firefly~0.garde7</Ivc>
    <Ivc>firefly~0.mem_invalid</Ivc>
    <Ivc>firefly~0.exclusive</Ivc>
    <Ivc>firefly~0.garde8</Ivc>
    </IvcSet>
    <IvcSet number="2">
    <Invariant>(((((firefly~0.shared + 0) + firefly~0.invalid) + firefly~0.dirty) &lt;= (First~0.First + firefly~0.exclusive)) or (not Sofar~0.Sofar))</Invariant>
    <Invariant>OK</Invariant>
    <Ivc>shared</Ivc>
    <Ivc>excludes8~0.X7</Ivc>
    <Ivc>procs</Ivc>
    <Ivc>excludes8~0.X8</Ivc>
    <Ivc>excludes8~0.X5</Ivc>
    <Ivc>excludes8~0.X6</Ivc>
    <Ivc>excludes8~0.X3</Ivc>
    <Ivc>excludes8~0.X4</Ivc>
    <Ivc>excludes8~0.X1</Ivc>
    <Ivc>Sofar~0.Sofar</Ivc>
    <Ivc>excludes8~0.X2</Ivc>
    <Ivc>firefly~0.invalid</Ivc>
    <Ivc>excludes8~0.excludes</Ivc>
    <Ivc>exclusive</Ivc>
    <Ivc>OK</Ivc>
    <Ivc>First~0.X</Ivc>
    <Ivc>dirty</Ivc>
    <Ivc>Sofar~0.X</Ivc>
    <Ivc>firefly~0.dirty</Ivc>
    <Ivc>firefly~0.e1</Ivc>
    <Ivc>firefly~0.i_invalid</Ivc>
    <Ivc>firefly~0.e4</Ivc>
    <Ivc>env</Ivc>
    <Ivc>firefly~0.e5</Ivc>
    <Ivc>firefly~0.e2</Ivc>
    <Ivc>firefly~0.e3</Ivc>
    <Ivc>firefly~0.e8</Ivc>
    <Ivc>firefly~0.shared</Ivc>
    <Ivc>firefly~0.e6</Ivc>
    <Ivc>firefly~0.e7</Ivc>
    <Ivc>First~0.First</Ivc>
    <Ivc>invalid</Ivc>
    <Ivc>firefly~0.garde5</Ivc>
    <Ivc>firefly~0.garde4</Ivc>
    <Ivc>firefly~0.garde6</Ivc>
    <Ivc>firefly~0.mem_invalid</Ivc>
    <Ivc>firefly~0.exclusive</Ivc>
    </IvcSet>
    <IvcSet number="3">
    <Invariant>((0 &lt;= (firefly~0.shared + (-1))) or (((3 * firefly~0.shared) + firefly~0.invalid) &lt;= First~0.First))</Invariant>
    <Invariant>(0 &lt;= firefly~0.shared)</Invariant>
    <Invariant>(((First~0.First + 0) + firefly~0.exclusive) &lt;= (First~0.First + 1))</Invariant>
    <Invariant>OK</Invariant>
    <Invariant>((firefly~0.exclusive = 0) or (0 &lt;= (firefly~0.exclusive + (-1))))</Invariant>
    <Invariant>((not (0 &lt;= (firefly~0.shared + (-1)))) or (0 &lt;= (firefly~0.shared + (-2))))</Invariant>
    <Ivc>shared</Ivc>
    <Ivc>excludes8~0.X7</Ivc>
    <Ivc>procs</Ivc>
    <Ivc>excludes8~0.X8</Ivc>
    <Ivc>excludes8~0.X6</Ivc>
    <Ivc>excludes8~0.X3</Ivc>
    <Ivc>excludes8~0.X4</Ivc>
    <Ivc>excludes8~0.X1</Ivc>
    <Ivc>Sofar~0.Sofar</Ivc>
    <Ivc>excludes8~0.X2</Ivc>
    <Ivc>firefly~0.invalid</Ivc>
    <Ivc>excludes8~0.excludes</Ivc>
    <Ivc>exclusive</Ivc>
    <Ivc>OK</Ivc>
    <Ivc>First~0.X</Ivc>
    <Ivc>dirty</Ivc>
    <Ivc>Sofar~0.X</Ivc>
    <Ivc>firefly~0.dirty</Ivc>
    <Ivc>firefly~0.e1</Ivc>
    <Ivc>firefly~0.i_invalid</Ivc>
    <Ivc>firefly~0.e4</Ivc>
    <Ivc>env</Ivc>
    <Ivc>firefly~0.e2</Ivc>
    <Ivc>firefly~0.e3</Ivc>
    <Ivc>firefly~0.e8</Ivc>
    <Ivc>firefly~0.shared</Ivc>
    <Ivc>firefly~0.e6</Ivc>
    <Ivc>firefly~0.e7</Ivc>
    <Ivc>First~0.First</Ivc>
    <Ivc>firefly~0.garde1</Ivc>
    <Ivc>firefly~0.garde3</Ivc>
    <Ivc>invalid</Ivc>
    <Ivc>firefly~0.garde5</Ivc>
    <Ivc>firefly~0.garde4</Ivc>
    <Ivc>firefly~0.garde6</Ivc>
    <Ivc>firefly~0.mem_invalid</Ivc>
    <Ivc>firefly~0.exclusive</Ivc>
    <Ivc>firefly~0.garde8</Ivc>
    </IvcSet>
    <IvcSet number="4">
    <Invariant>OK</Invariant>
    <Invariant>(firefly~0.dirty &gt;= 0)</Invariant>
    <Invariant>(firefly~0.exclusive &gt;= 0)</Invariant>
    <Ivc>shared</Ivc>
    <Ivc>excludes8~0.X7</Ivc>
    <Ivc>procs</Ivc>
    <Ivc>excludes8~0.X8</Ivc>
    <Ivc>excludes8~0.X5</Ivc>
    <Ivc>excludes8~0.X6</Ivc>
    <Ivc>excludes8~0.X3</Ivc>
    <Ivc>excludes8~0.X4</Ivc>
    <Ivc>excludes8~0.X1</Ivc>
    <Ivc>Sofar~0.Sofar</Ivc>
    <Ivc>excludes8~0.X2</Ivc>
    <Ivc>firefly~0.invalid</Ivc>
    <Ivc>excludes8~0.excludes</Ivc>
    <Ivc>exclusive</Ivc>
    <Ivc>OK</Ivc>
    <Ivc>First~0.X</Ivc>
    <Ivc>dirty</Ivc>
    <Ivc>Sofar~0.X</Ivc>
    <Ivc>firefly~0.dirty</Ivc>
    <Ivc>firefly~0.e1</Ivc>
    <Ivc>firefly~0.i_invalid</Ivc>
    <Ivc>firefly~0.e4</Ivc>
    <Ivc>env</Ivc>
    <Ivc>firefly~0.e5</Ivc>
    <Ivc>firefly~0.e2</Ivc>
    <Ivc>firefly~0.e3</Ivc>
    <Ivc>firefly~0.e8</Ivc>
    <Ivc>firefly~0.shared</Ivc>
    <Ivc>firefly~0.e6</Ivc>
    <Ivc>firefly~0.e7</Ivc>
    <Ivc>First~0.First</Ivc>
    <Ivc>invalid</Ivc>
    <Ivc>firefly~0.garde2</Ivc>
    <Ivc>firefly~0.garde5</Ivc>
    <Ivc>firefly~0.garde4</Ivc>
    <Ivc>firefly~0.garde7</Ivc>
    <Ivc>firefly~0.mem_invalid</Ivc>
    <Ivc>firefly~0.exclusive</Ivc>
    </IvcSet>
  </Property>
</Results>